pyjsondatabase.py
pyjsondatabase-0.0.1.dist-info/WHEEL
pyjsondatabase-0.0.1.dist-info/METADATA
pyjsondatabase-0.0.1.dist-info/RECORD
