Metadata-Version: 2.1
Name: pyjsondatabase
Version: 0.0.1
Summary: Simple dictionary-based database
License: Reflect Solutions
Author: Xenely
Requires-Python: >=3.7,<4.0
Classifier: License :: Other/Proprietary License
Classifier: Programming Language :: Python :: 3
Classifier: Programming Language :: Python :: 3.7
Classifier: Programming Language :: Python :: 3.8
Classifier: Programming Language :: Python :: 3.9
Classifier: Programming Language :: Python :: 3.10
Classifier: Programming Language :: Python :: 3.11
